py_miraie_ac/__init__.py
py_miraie_ac/api.py
py_miraie_ac/broker.py
py_miraie_ac/constants.py
py_miraie_ac/device.py
py_miraie_ac/deviceStatus.py
py_miraie_ac/enums.py
py_miraie_ac/exceptions.py
py_miraie_ac/home.py
py_miraie_ac/test.py
py_miraie_ac/user.py
py_miraie_ac/utils.py
py_miraie_ac-0.1.10.dist-info/LICENSE
py_miraie_ac-0.1.10.dist-info/METADATA
py_miraie_ac-0.1.10.dist-info/WHEEL
py_miraie_ac-0.1.10.dist-info/top_level.txt
py_miraie_ac-0.1.10.dist-info/RECORD
