Metadata-Version: 2.1
Name: py-miraie-ac
Version: 0.1.10
Summary: A package to control and read MirAIe Aircons by Panasonic
Home-page: https://github.com/milothomas/py-miraie-ac
Author: Milo Thomas
Author-email: 20719501+milothomas@users.noreply.github.com
Project-URL: Bug Tracker, https://github.com/milothomas/py-miraie-ac/issues
Classifier: Programming Language :: Python :: 3
Classifier: License :: OSI Approved :: GNU General Public License v3 (GPLv3)
Classifier: Operating System :: OS Independent
Requires-Python: >=3.6
License-File: LICENSE
Requires-Dist: aiohttp >=3.8.4
Requires-Dist: paho-mqtt >=1.6.1
